{
	"databaseType": "Sybase",
	"inputEntity": [
	],
	"inputParameters": [
		{
			"attributeId": "",
			"bddType": "char",
			"dataType": "CHAR",
			"direction": "in",
			"entityId": "",
			"format": "",
			"name": "@i_operacion",
			"type": "CONSTANT",
			"value": "R"
		},
		{
			"attributeId": "",
			"bddType": "int",
			"dataType": "INT",
			"direction": "in",
			"entityId": "",
			"format": "",
			"name": "@t_trn",
			"type": "CONSTANT",
			"value": "706715"
		},
		{
			"attributeId": "",
			"bddType": "varchar",
			"dataType": "VARCHAR",
			"direction": "in",
			"entityId": "",
			"format": "",
			"name": "@i_cuenta",
			"type": "CUSTOM",
			"value": "cuenta"
		}
	],
	"name": "BLI_ConsultarOrigen",
	"outputEntity": [
	],
	"outputParameters": [
	],
	"patternId": "BLI8860_bli_consultarorigen",
	"patternName": "BLI_ConsultarOrigen",
	"patternType": "Bli",
	"queries": [
		{
			"_idQuery": "44bcd713-e551-478d-bf65-3ea2997cd7ac",
			"isMapReturn": true,
			"isReturn": true,
			"isSingleResult": false,
			"numberQuery": 6,
			"queryName": "SELECT"
		}
	],
	"resultSets": [
		{
			"_idQuery": "44bcd713-e551-478d-bf65-3ea2997cd7ac",
			"columns": [
				{
					"attributeId": "AT95_BANCOSHW998",
					"entityId": "EN_2DWTFTYSE_998",
					"format": "",
					"name": "Numero cuenta",
					"position": 1,
					"type": "ATTRIBUTE"
				},
				{
					"attributeId": "AT61_FECHACEE998",
					"entityId": "EN_2DWTFTYSE_998",
					"format": "",
					"name": "Fecha creacion",
					"position": 2,
					"type": "ATTRIBUTE"
				},
				{
					"attributeId": "AT96_FECHAMII998",
					"entityId": "EN_2DWTFTYSE_998",
					"format": "",
					"name": "Fecha modificacion",
					"position": 3,
					"type": "ATTRIBUTE"
				},
				{
					"attributeId": "AT97_CLIENTEE998",
					"entityId": "EN_2DWTFTYSE_998",
					"format": "",
					"name": "Id cliente",
					"position": 4,
					"type": "ATTRIBUTE"
				},
				{
					"attributeId": "AT87_SALDOWDJ998",
					"entityId": "EN_2DWTFTYSE_998",
					"format": "",
					"name": "Saldo",
					"position": 5,
					"type": "ATTRIBUTE"
				},
				{
					"attributeId": "AT6203_6202LOIL998",
					"entityId": "EN_2DWTFTYSE_998",
					"format": "",
					"name": "Tipo cuenta",
					"position": 6,
					"type": "ATTRIBUTE"
				}
			],
			"number": 1,
			"singleResult": false
		}
	],
	"returnEntity": [
		{
			"entityId": "EN_2DWTFTYSE_998",
			"module": {
				"moduleId": "CNTAS",
				"moduleName": "CUENTAS"
			},
			"name": "Cuenta"
		}
	],
	"serverName": "CENTRAL",
	"serviceID": "cobis.g3_sp_busqueda_cliente",
	"type": "SP",
	"typeMapping": "MAPJava"
}
