{
	"autoCrudStr": "F",
	"cobisPattern": "None",
	"cobisPatternId": 0,
	"commands": [
		{
			"action": null,
			"causesValidation": false,
			"causesValidationAsString": "F",
			"close": false,
			"closeAsString": "F",
			"commandType": 0,
			"customEvents": [
				{
					"commandEventType": {
						"availableExecutionType": 7,
						"description": "Permite personalizar la acci\u00f3n a ejecutar de un command o de un ActionControl",
						"eventId": 10,
						"name": "ExecuteCommand"
					},
					"customEventId": "CECM_010CM_TCNTASPN_A89_453",
					"customizationLayer": 0,
					"customizationLayerDescription": "ECU",
					"enabled": "T",
					"eventActions": [
						{
							"actionArgs": [
							],
							"actionId": "CUSTOM",
							"actionType": "CUSTOM"
						}
					],
					"executionType": 7,
					"filter": null,
					"isEnabled": true
				}
			],
			"customizationLayer": 0,
			"customizationLayerDescription": "ECU",
			"enabled": 4095,
			"group": null,
			"id": {
				"commandId": "CM_TCNTASPN_A89"
			},
			"imageId": null,
			"isCustomized": false,
			"label": {
				"defaultValue": {
					"$ref": "../../../../CNTAS/assets/languages/CNTAS.json#/CNTAS/LBL/LBL_CNTAS_GUARDAROD_73049"
				},
				"labelId": "LBL_CNTAS_GUARDAROD_73049",
				"moduleId": "CNTAS"
			},
			"layoutType": "Command",
			"name": "Command1",
			"options": 0,
			"order": 1,
			"showInMode": 4095,
			"userControl": {
				"type": "A",
				"userControlId": "Button"
			},
			"validationGroup": null
		}
	],
	"customEvents": [
	],
	"customizationLayer": 0,
	"customizationLayerDescription": "ECU",
	"graphicSupportStr": "F",
	"header": null,
	"id": {
		"moduleId": "CNTAS",
		"subModuleId": "ADMIN",
		"taskId": "T_CNTASPNFEFZNV_404",
		"version": "1.0.0"
	},
	"isCustomized": false,
	"isImported": false,
	"mainViewContainerId": "VC_FRMINSERAN_314404",
	"modeEnabled": 4095,
	"name": {
		"$ref": "../../../../CNTAS/relations/componentKeys.json#/ADMIN/Forms/T_CNTASPNFEFZNV_404/name"
	},
	"setFocus": false,
	"tempSaveStr": "F",
	"viewContainers": [
		{
			"breadcrumbs": "Automatic",
			"collapsedStr": "F",
			"colSpan": 1,
			"columnsNum": 1,
			"componentStyle": null,
			"customEvents": [
			],
			"customizationLayer": 0,
			"customizationLayerDescription": "ECU",
			"enabled": 4095,
			"id": {
				"moduleId": "CNTAS",
				"subModuleId": "ADMIN",
				"taskId": "T_CNTASPNFEFZNV_404",
				"taskVersion": "1.0.0",
				"viewContainerId": "VC_FRMINSERAN_314404"
			},
			"isCustomized": false,
			"layoutType": "Group",
			"name": "frmInsertarCuenta",
			"options": 0,
			"responsiveLayouts": null,
			"responsivity": false,
			"style": null,
			"view": {
				"groups": [
					{
						"collapsedStr": "F",
						"colSpan": 1,
						"columnsNum": 3,
						"componentStyle": null,
						"customEvents": [
						],
						"enabled": 4095,
						"entity": {
							"$ref": "../../../../CNTAS/entities/EN_2DWTFTYSE_998.json#"
						},
						"eventType": 0,
						"groupId": "G_FRMINSENUU_407475",
						"htmlSection": "F",
						"independentValidation": "F",
						"isCustomized": false,
						"layoutType": "Group",
						"name": "Group1752",
						"order": 1,
						"orientation": "V",
						"responsiveLayouts": null,
						"responsivity": false,
						"style": null,
						"visible": 4095,
						"visualAttributes": [
							{
								"aggregate": null,
								"aggregateId": null,
								"attribute": {
									"$ref": "../../../../CNTAS/entities/EN_2DWTFTYSE_998.json#/attributes/AT97_CLIENTEE998"
								},
								"attributeValidations": [
								],
								"colSpan": 1,
								"componentInGrid": false,
								"componentStyle": null,
								"customEvents": [
								],
								"customizationLayer": 0,
								"customizationLayerDescription": "ECU",
								"enabled": 4095,
								"format": "",
								"include": 4095,
								"isCustomized": false,
								"label": {
									"defaultValue": {
										"$ref": "../../../../CNTAS/assets/languages/CNTAS.json#/CNTAS/LBL/LBL_CNTAS_CLIENTEDE_28851"
									},
									"labelId": "LBL_CNTAS_CLIENTEDE_28851",
									"moduleId": "CNTAS"
								},
								"maxRecords": null,
								"name": "cliente",
								"options": 0,
								"order": 3,
								"readOnly": 8,
								"responsiveLayouts": null,
								"responsivity": false,
								"sizeWidthComposite": null,
								"style": null,
								"textRows": 0,
								"userControl": {
									"type": "I",
									"userControlId": "TextInputBox"
								},
								"visible": 4095,
								"visualAttributeId": "VA_CLIENTEHAEBNJLU_940475",
								"width": null,
								"widthComposite": "D"
							},
							{
								"aggregate": null,
								"aggregateId": null,
								"attribute": {
									"$ref": "../../../../CNTAS/entities/EN_2DWTFTYSE_998.json#/attributes/AT87_SALDOWDJ998"
								},
								"attributeValidations": [
								],
								"colSpan": 1,
								"componentInGrid": false,
								"componentStyle": null,
								"customEvents": [
								],
								"customizationLayer": 0,
								"customizationLayerDescription": "ECU",
								"enabled": 4095,
								"format": "",
								"include": 4095,
								"isCustomized": false,
								"label": {
									"defaultValue": {
										"$ref": "../../../../CNTAS/assets/languages/CNTAS.json#/CNTAS/LBL/LBL_CNTAS_SALDONBGU_29941"
									},
									"labelId": "LBL_CNTAS_SALDONBGU_29941",
									"moduleId": "CNTAS"
								},
								"maxRecords": null,
								"name": "saldo",
								"options": 0,
								"order": 2,
								"readOnly": 8,
								"responsiveLayouts": null,
								"responsivity": false,
								"sizeWidthComposite": null,
								"style": null,
								"textRows": 0,
								"userControl": {
									"type": "I",
									"userControlId": "TextInputBox"
								},
								"visible": 4095,
								"visualAttributeId": "VA_SALDOIGQWWZMUHH_207475",
								"width": null,
								"widthComposite": "D"
							},
							{
								"aggregate": null,
								"aggregateId": null,
								"attribute": {
									"$ref": "../../../../CNTAS/entities/EN_2DWTFTYSE_998.json#/attributes/AT30_TIPOCUAT998"
								},
								"attributeValidations": [
								],
								"cacheDuration": 0,
								"catalogName": "g2_cl_tipo_cuenta",
								"colSpan": 1,
								"componentInGrid": false,
								"componentStyle": null,
								"customEvents": [
								],
								"customizationLayer": 0,
								"customizationLayerDescription": "ECU",
								"enabled": 4095,
								"entityQuery": null,
								"include": 4095,
								"isCustomized": false,
								"label": {
									"defaultValue": {
										"$ref": "../../../../CNTAS/assets/languages/CNTAS.json#/CNTAS/LBL/LBL_CNTAS_TIPOCUETA_93397"
									},
									"labelId": "LBL_CNTAS_TIPOCUETA_93397",
									"moduleId": "CNTAS"
								},
								"maxRecords": null,
								"minChars": null,
								"name": "tipoCuenta",
								"options": 0,
								"order": 1,
								"queryId": null,
								"queryMemberText": {
									"attribute": {
										"attributeId": null,
										"name": null
									},
									"queryMemberId": null
								},
								"queryMemberValue": {
									"attribute": {
										"attributeId": null,
										"name": null
									},
									"queryMemberId": null
								},
								"queryModule": null,
								"queryVersion": null,
								"readOnly": 8,
								"responsiveLayouts": null,
								"responsivity": false,
								"sizeWidthComposite": null,
								"style": null,
								"type": null,
								"userControl": {
									"type": "I",
									"userControlId": "ComboBox"
								},
								"visible": 4095,
								"visualAttributeId": "VA_TIPOCUENTAJEOUI_981475",
								"width": null,
								"widthComposite": "D"
							}
						]
					}
				],
				"id": {
					"version": "1.0.0",
					"viewId": "VW_FRMINSERER_475"
				},
				"metadataVersion": "7.2.0.2020",
				"modules": [
					{
						"moduleId": "CNTAS"
					}
				],
				"name": "View of frmInsertarCuenta"
			}
		}
	]
}
