{
	"autoCrudStr": "F",
	"cobisPattern": "None",
	"cobisPatternId": 0,
	"commands": [
		{
			"action": null,
			"causesValidation": false,
			"causesValidationAsString": "F",
			"close": false,
			"closeAsString": "F",
			"commandType": 0,
			"customEvents": [
			],
			"customizationLayer": 0,
			"customizationLayerDescription": "ECU",
			"enabled": 4095,
			"group": null,
			"id": {
				"commandId": "CM_TCNTASUX__6_"
			},
			"imageId": null,
			"isCustomized": false,
			"label": {
				"defaultValue": {
					"$ref": "../../../../CNTAS/assets/languages/CNTAS.json#/CNTAS/LBL/LBL_CNTAS_TARANSFRR_28094"
				},
				"labelId": "LBL_CNTAS_TARANSFRR_28094",
				"moduleId": "CNTAS"
			},
			"layoutType": "Command",
			"name": "Command1",
			"options": 0,
			"order": 1,
			"showInMode": 4095,
			"userControl": {
				"type": "A",
				"userControlId": "Button"
			},
			"validationGroup": null
		}
	],
	"customEvents": [
	],
	"customizationLayer": 0,
	"customizationLayerDescription": "ECU",
	"graphicSupportStr": "F",
	"header": null,
	"id": {
		"moduleId": "CNTAS",
		"subModuleId": "ADMIN",
		"taskId": "T_CNTASUXJTKMDW_656",
		"version": "1.0.0"
	},
	"isCustomized": false,
	"isImported": false,
	"mainViewContainerId": "VC_CUENTADEON_686656",
	"modeEnabled": 4095,
	"name": {
		"$ref": "../../../../CNTAS/relations/componentKeys.json#/ADMIN/Forms/T_CNTASUXJTKMDW_656/name"
	},
	"setFocus": false,
	"tempSaveStr": "F",
	"viewContainers": [
		{
			"breadcrumbs": "Automatic",
			"collapsedStr": "F",
			"colSpan": 1,
			"columnsNum": 1,
			"componentStyle": null,
			"customEvents": [
			],
			"customizationLayer": 0,
			"customizationLayerDescription": "ECU",
			"enabled": 4095,
			"id": {
				"moduleId": "CNTAS",
				"subModuleId": "ADMIN",
				"taskId": "T_CNTASUXJTKMDW_656",
				"taskVersion": "1.0.0",
				"viewContainerId": "VC_CUENTADEON_686656"
			},
			"isCustomized": false,
			"layoutType": "Group",
			"name": "formCuentaDestino",
			"options": 0,
			"responsiveLayouts": null,
			"responsivity": false,
			"style": null,
			"view": {
				"groups": [
					{
						"collapsedStr": "F",
						"colSpan": 1,
						"columnsNum": 2,
						"componentStyle": null,
						"customEvents": [
						],
						"enabled": 4095,
						"entity": {
							"$ref": "../../../../CNTAS/entities/EN_FILTROCUE_372.json#"
						},
						"eventType": 0,
						"groupId": "G_CUENTADNES_740794",
						"htmlSection": "F",
						"independentValidation": "F",
						"isCustomized": false,
						"layoutType": "Group",
						"name": "Group2770",
						"order": 2,
						"orientation": "V",
						"responsiveLayouts": null,
						"responsivity": false,
						"style": null,
						"visible": 4095,
						"visualAttributes": [
							{
								"aggregate": null,
								"aggregateId": null,
								"attribute": {
									"$ref": "../../../../CNTAS/entities/EN_FILTROCUE_372.json#/attributes/AT84_CUENTADD372"
								},
								"attributeValidations": [
								],
								"colSpan": 1,
								"componentInGrid": false,
								"componentStyle": null,
								"customEvents": [
								],
								"customizationLayer": 0,
								"customizationLayerDescription": "ECU",
								"enabled": 4095,
								"format": "",
								"include": 4095,
								"isCustomized": false,
								"label": {
									"defaultValue": {
										"$ref": "../../../../CNTAS/assets/languages/CNTAS.json#/CNTAS/LBL/LBL_CNTAS_NOCUENTAA_90338"
									},
									"labelId": "LBL_CNTAS_NOCUENTAA_90338",
									"moduleId": "CNTAS"
								},
								"maxRecords": null,
								"name": "cuentaD",
								"options": 0,
								"order": 1,
								"readOnly": 8,
								"responsiveLayouts": null,
								"responsivity": false,
								"sizeWidthComposite": null,
								"style": null,
								"textRows": 0,
								"userControl": {
									"type": "I",
									"userControlId": "TextInputBox"
								},
								"visible": 4095,
								"visualAttributeId": "VA_CUENTADMGVBDHZW_384794",
								"width": null,
								"widthComposite": "D"
							},
							{
								"aggregate": null,
								"aggregateId": null,
								"attributeValidations": [
								],
								"colSpan": 1,
								"componentInGrid": false,
								"componentStyle": null,
								"customEvents": [
								],
								"customizationLayer": 0,
								"customizationLayerDescription": "ECU",
								"enabled": 4095,
								"entityQuery": "EN_CUENTADSE_522",
								"imageId": "fa fa-search",
								"include": 4095,
								"isCustomized": false,
								"label": {
									"defaultValue": {
										"$ref": "../../../../CNTAS/assets/languages/CNTAS.json#/CNTAS/LBL/LBL_CNTAS_BUSCARUYH_74684"
									},
									"labelId": "LBL_CNTAS_BUSCARUYH_74684",
									"moduleId": "CNTAS"
								},
								"maxRecords": null,
								"name": "",
								"options": 0,
								"order": 2,
								"queryId": "Q_CUENITTE_VP60",
								"queryModule": "CNTAS",
								"queryVersion": "1.0.0",
								"responsiveLayouts": null,
								"responsivity": false,
								"sizeWidthComposite": null,
								"style": null,
								"userControl": {
									"type": "A",
									"userControlId": "Button"
								},
								"visible": 4095,
								"visualAttributeId": "VA_VABUTTONDASSXAJ_564794",
								"width": null,
								"widthComposite": "D"
							}
						]
					},
					{
						"collapsedStr": "F",
						"colSpan": 1,
						"columnsNum": 1,
						"componentStyle": null,
						"customEvents": [
						],
						"enabled": 4095,
						"entity": {
							"$ref": "../../../../CNTAS/entities/EN_CUENTADSE_522.json#"
						},
						"eventType": 0,
						"groupId": "G_CUENTADNOS_257794",
						"htmlSection": "F",
						"independentValidation": "F",
						"isCustomized": false,
						"layoutType": "Group",
						"name": "Group2455",
						"order": 3,
						"orientation": "V",
						"queryView": {
							"actionDesign": "Button",
							"actions": [
							],
							"allowPaging": false,
							"allowPagingStr": "F",
							"allowSorting": false,
							"allowSortingStr": "F",
							"autoSync": null,
							"componentStyle": null,
							"confirmRowDeletion": false,
							"confirmRowDeletionStr": "F",
							"customEvents": [
							],
							"customizationLayer": 0,
							"customizationLayerDescription": "ECU",
							"customUrlDialog": null,
							"deleteCommandEnabled": false,
							"deleteCommandEnabledStr": "F",
							"dialogTitleLabelId": null,
							"editCommandEnabled": false,
							"editCommandEnabledStr": "F",
							"editMode": "0",
							"entityName": {
								"$ref": "../../../../CNTAS/entities/EN_CUENTADSE_522.json#/name"
							},
							"hasDetail": false,
							"hasDetailString": "F",
							"height": null,
							"includeQueryMembers": [
								"AT52_BANCODZN522",
								"AT52_FECHACNC522",
								"AT61_FECHAMAO522",
								"AT11_CLIENTEE522",
								"AT28_SALDOKWQ522"
							],
							"insertCommandEnabled": false,
							"insertCommandEnabledStr": "F",
							"isCustomized": false,
							"modalSize": null,
							"modeSelection": "None",
							"moduleIdDialog": null,
							"multiSelectEnabledStr": "F",
							"name": "QV_AR60_BTV68",
							"options": 0,
							"pageSize": null,
							"query": {
								"$ref": "../../../../CNTAS/ADMIN/queries/Q_CUENITTE_VP60.json#"
							},
							"queryId": "Q_CUENITTE_VP60",
							"queryVersion": "1.0.0",
							"queryViewCustomActions": [
							],
							"queryViewId": "QV_AR60_BTV68",
							"queryViewType": "Grid",
							"rowCommandAppearance": 0,
							"style": null,
							"subModuleIdDialog": null,
							"taskIdDialog": null,
							"taskVersionDialog": null,
							"typeFormDialog": null,
							"userControl": {
								"customizationLayer": 0,
								"customizationLayerDescription": "ECU",
								"description": "Designer Grid",
								"name": "Designer Grid",
								"type": "I",
								"userControlId": "Grid"
							},
							"viewContainerIdDialog": null
						},
						"queryViewId": "QV_AR60_BTV68",
						"responsiveLayouts": null,
						"responsivity": false,
						"style": null,
						"visible": 4095,
						"visualAttributes": [
							{
								"aggregate": null,
								"aggregateId": null,
								"attribute": {
									"$ref": "../../../../CNTAS/entities/EN_CUENTADSE_522.json#/attributes/AT61_FECHAMAO522"
								},
								"attributeValidations": [
								],
								"colSpan": 1,
								"componentInGrid": true,
								"componentStyle": null,
								"customEvents": [
								],
								"customizationLayer": 0,
								"customizationLayerDescription": "ECU",
								"enabled": 4095,
								"include": 4095,
								"isCustomized": false,
								"maxRecords": null,
								"name": "fechaModificacion",
								"options": 0,
								"order": 3,
								"readOnly": 8,
								"responsiveLayouts": null,
								"responsivity": false,
								"sizeWidthComposite": null,
								"style": null,
								"textRows": 0,
								"userControl": {
									"type": "I",
									"userControlId": "TextInputBox"
								},
								"visible": 4095,
								"visualAttributeId": "VA_TEXTINPUTBOXBMQ_214794",
								"width": null,
								"widthComposite": "D"
							},
							{
								"aggregate": null,
								"aggregateId": null,
								"attribute": {
									"$ref": "../../../../CNTAS/entities/EN_CUENTADSE_522.json#/attributes/AT28_SALDOKWQ522"
								},
								"attributeValidations": [
								],
								"colSpan": 1,
								"componentInGrid": true,
								"componentStyle": null,
								"customEvents": [
								],
								"customizationLayer": 0,
								"customizationLayerDescription": "ECU",
								"enabled": 4095,
								"include": 4095,
								"isCustomized": false,
								"maxRecords": null,
								"name": "saldo",
								"options": 0,
								"order": 5,
								"readOnly": 8,
								"responsiveLayouts": null,
								"responsivity": false,
								"sizeWidthComposite": null,
								"style": null,
								"textRows": 0,
								"userControl": {
									"type": "I",
									"userControlId": "TextInputBox"
								},
								"visible": 4095,
								"visualAttributeId": "VA_TEXTINPUTBOXMGD_845794",
								"width": null,
								"widthComposite": "D"
							},
							{
								"aggregate": null,
								"aggregateId": null,
								"attribute": {
									"$ref": "../../../../CNTAS/entities/EN_CUENTADSE_522.json#/attributes/AT52_FECHACNC522"
								},
								"attributeValidations": [
								],
								"colSpan": 1,
								"componentInGrid": true,
								"componentStyle": null,
								"customEvents": [
								],
								"customizationLayer": 0,
								"customizationLayerDescription": "ECU",
								"enabled": 4095,
								"include": 4095,
								"isCustomized": false,
								"maxRecords": null,
								"name": "fechaCreacion",
								"options": 0,
								"order": 2,
								"readOnly": 8,
								"responsiveLayouts": null,
								"responsivity": false,
								"sizeWidthComposite": null,
								"style": null,
								"textRows": 0,
								"userControl": {
									"type": "I",
									"userControlId": "TextInputBox"
								},
								"visible": 4095,
								"visualAttributeId": "VA_TEXTINPUTBOXOLS_130794",
								"width": null,
								"widthComposite": "D"
							},
							{
								"aggregate": null,
								"aggregateId": null,
								"attribute": {
									"$ref": "../../../../CNTAS/entities/EN_CUENTADSE_522.json#/attributes/AT52_BANCODZN522"
								},
								"attributeValidations": [
								],
								"colSpan": 1,
								"componentInGrid": true,
								"componentStyle": null,
								"customEvents": [
								],
								"customizationLayer": 0,
								"customizationLayerDescription": "ECU",
								"enabled": 4095,
								"include": 4095,
								"isCustomized": false,
								"maxRecords": null,
								"name": "banco",
								"options": 0,
								"order": 1,
								"readOnly": 8,
								"responsiveLayouts": null,
								"responsivity": false,
								"sizeWidthComposite": null,
								"style": null,
								"textRows": 0,
								"userControl": {
									"type": "I",
									"userControlId": "TextInputBox"
								},
								"visible": 4095,
								"visualAttributeId": "VA_TEXTINPUTBOXRXU_885794",
								"width": null,
								"widthComposite": "D"
							},
							{
								"aggregate": null,
								"aggregateId": null,
								"attribute": {
									"$ref": "../../../../CNTAS/entities/EN_CUENTADSE_522.json#/attributes/AT11_CLIENTEE522"
								},
								"attributeValidations": [
								],
								"colSpan": 1,
								"componentInGrid": true,
								"componentStyle": null,
								"customEvents": [
								],
								"customizationLayer": 0,
								"customizationLayerDescription": "ECU",
								"enabled": 4095,
								"include": 4095,
								"isCustomized": false,
								"maxRecords": null,
								"name": "cliente",
								"options": 0,
								"order": 4,
								"readOnly": 8,
								"responsiveLayouts": null,
								"responsivity": false,
								"sizeWidthComposite": null,
								"style": null,
								"textRows": 0,
								"userControl": {
									"type": "I",
									"userControlId": "TextInputBox"
								},
								"visible": 4095,
								"visualAttributeId": "VA_TEXTINPUTBOXTNV_365794",
								"width": null,
								"widthComposite": "D"
							}
						]
					},
					{
						"collapsedStr": "F",
						"colSpan": 1,
						"columnsNum": 2,
						"componentStyle": null,
						"customEvents": [
						],
						"enabled": 4095,
						"entity": {
							"$ref": "../../../../CNTAS/entities/EN_2DWTFTYSE_998.json#"
						},
						"eventType": 0,
						"groupId": "G_CUENTADNSS_314794",
						"htmlSection": "F",
						"independentValidation": "F",
						"isCustomized": false,
						"layoutType": "Group",
						"name": "Group2643",
						"order": 4,
						"orientation": "V",
						"responsiveLayouts": null,
						"responsivity": false,
						"style": null,
						"visible": 4095,
						"visualAttributes": [
							{
								"aggregate": null,
								"aggregateId": null,
								"attribute": {
									"$ref": "../../../../CNTAS/entities/EN_2DWTFTYSE_998.json#/attributes/AT87_SALDOWDJ998"
								},
								"attributeValidations": [
								],
								"colSpan": 1,
								"componentInGrid": false,
								"componentStyle": null,
								"customEvents": [
								],
								"customizationLayer": 0,
								"customizationLayerDescription": "ECU",
								"enabled": 4095,
								"format": "",
								"include": 4095,
								"isCustomized": false,
								"label": {
									"defaultValue": {
										"$ref": "../../../../CNTAS/assets/languages/CNTAS.json#/CNTAS/LBL/LBL_CNTAS_VALORATRE_89141"
									},
									"labelId": "LBL_CNTAS_VALORATRE_89141",
									"moduleId": "CNTAS"
								},
								"maxRecords": null,
								"name": "saldo",
								"options": 0,
								"order": 1,
								"readOnly": 8,
								"responsiveLayouts": null,
								"responsivity": false,
								"sizeWidthComposite": null,
								"style": null,
								"textRows": 0,
								"userControl": {
									"type": "I",
									"userControlId": "TextInputBox"
								},
								"visible": 4095,
								"visualAttributeId": "VA_SALDOYUMXUAWSLG_669794",
								"width": null,
								"widthComposite": "D"
							}
						]
					},
					{
						"collapsedStr": "F",
						"colSpan": 1,
						"columnsNum": 1,
						"componentStyle": null,
						"customEvents": [
						],
						"enabled": 4095,
						"eventType": 0,
						"groupId": "G_CUENTADOSI_849794",
						"htmlSection": "F",
						"independentValidation": "F",
						"isCustomized": false,
						"layoutType": "Group",
						"name": "Group1218",
						"order": 1,
						"orientation": "V",
						"responsiveLayouts": null,
						"responsivity": false,
						"style": null,
						"visible": 4095,
						"visualAttributes": [
							{
								"aggregate": null,
								"aggregateId": null,
								"colSpan": 1,
								"componentInGrid": false,
								"componentStyle": null,
								"customEvents": [
								],
								"customizationLayer": 0,
								"customizationLayerDescription": "ECU",
								"include": 4095,
								"isCustomized": false,
								"label": {
									"defaultValue": {
										"$ref": "../../../../CNTAS/assets/languages/CNTAS.json#/CNTAS/LBL/LBL_CNTAS_CUENTADTT_17895"
									},
									"labelId": "LBL_CNTAS_CUENTADTT_17895",
									"moduleId": "CNTAS"
								},
								"maxRecords": null,
								"name": "VA_VASIMPLELABELLL_858794",
								"options": 0,
								"order": 1,
								"responsiveLayouts": null,
								"responsivity": false,
								"sizeWidthComposite": null,
								"style": null,
								"userControl": {
									"userControlId": "SimpleLabel"
								},
								"visible": 4095,
								"visualAttributeId": "VA_VASIMPLELABELLL_858794",
								"width": null,
								"widthComposite": "D"
							}
						]
					}
				],
				"id": {
					"version": "1.0.0",
					"viewId": "VW_CUENTADEIO_794"
				},
				"metadataVersion": "7.2.0.2020",
				"modules": [
					{
						"moduleId": "CNTAS"
					}
				],
				"name": "View of formCuentaDestino"
			}
		}
	]
}
